nyoka/PMML44.py
nyoka/PMML44Super.py
nyoka/__init__.py
nyoka/build.py
nyoka/metadata.py
nyoka/base/__init__.py
nyoka/base/constants.py
nyoka/custom/__init__.py
nyoka/custom/trendminer.py
nyoka/lgbm/__init__.py
nyoka/lgbm/lgb_to_pmml.py
nyoka/pipeline/__init__.py
nyoka/pipeline/pipeline_to_pmml.py
nyoka/preprocessing/__init__.py
nyoka/skl/__init__.py
nyoka/skl/pre_process.py
nyoka/skl/skl_to_pmml.py
nyoka/statsmodels/__init__.py
nyoka/statsmodels/exponential_smoothing.py
nyoka/statsmodels/statsmodels_to_pmml.py
nyoka/xgboost/__init__.py
nyoka/xgboost/xgboost_to_pmml.py
nyoka-5.5.0.dist-info/LICENSE
nyoka-5.5.0.dist-info/METADATA
nyoka-5.5.0.dist-info/WHEEL
nyoka-5.5.0.dist-info/top_level.txt
nyoka-5.5.0.dist-info/RECORD
