Metadata-Version: 2.1
Name: nyoka
Version: 5.5.0
Summary: Python library for converting a large number of ML models to PMML
Home-page: https://github.com/softwareag/nyoka
Author: maintainer
Author-email: maintainer@nyoka.org
License: Apache Software License
Classifier: Development Status :: 5 - Production/Stable
Classifier: License :: OSI Approved :: Apache Software License
Classifier: Operating System :: OS Independent
Classifier: Programming Language :: Python :: 3.6
Classifier: Programming Language :: Python :: 3.7
Classifier: Programming Language :: Python :: 3.8
Classifier: Intended Audience :: Developers
Classifier: Topic :: Scientific/Engineering :: Artificial Intelligence
Requires-Python: >= 3.6
License-File: LICENSE
Requires-Dist: lxml
